easy_utils/__init__.py
easy_utils-0.0.2.dist-info/METADATA
easy_utils-0.0.2.dist-info/RECORD
easy_utils-0.0.2.dist-info/WHEEL
easy_utils-0.0.2.dist-info/top_level.txt
