Metadata-Version: 2.1
Name: easy-utils
Version: 0.0.2
Summary: Easy to use utilities, like logging, downloading, uploading, and file checking
Home-page: https://github.com/deadlift1226/easy_utils.git
Author: Dane Morgan
Author-email: danemorgan91@gmail.com
License: UNKNOWN
Platform: UNKNOWN
Classifier: Programming Language :: Python :: 3
Classifier: License :: OSI Approved :: MIT License
Classifier: Operating System :: OS Independent
Requires-Dist: colorama
